{
	"configurations" : 
	[
		{
			"directories" : 
			[
				{
					"build" : ".",
					"jsonFile" : "directory-.-Debug-f5ebdc15457944623624.json",
					"minimumCMakeVersion" : 
					{
						"string" : "3.22"
					},
					"projectIndex" : 0,
					"source" : ".",
					"targetIndexes" : 
					[
						0,
						1
					]
				}
			],
			"name" : "Debug",
			"projects" : 
			[
				{
					"directoryIndexes" : 
					[
						0
					],
					"name" : "AttributeStruct",
					"targetIndexes" : 
					[
						0,
						1
					]
				}
			],
			"targets" : 
			[
				{
					"directoryIndex" : 0,
					"id" : "AttributeStruct::@6890427a1f51a3e7e1df",
					"jsonFile" : "target-AttributeStruct-Debug-d58cc59f2de809193a52.json",
					"name" : "AttributeStruct",
					"projectIndex" : 0
				},
				{
					"directoryIndex" : 0,
					"id" : "hello::@6890427a1f51a3e7e1df",
					"jsonFile" : "target-hello-Debug-a9d5805c56b3278c5b85.json",
					"name" : "hello",
					"projectIndex" : 0
				}
			]
		}
	],
	"kind" : "codemodel",
	"paths" : 
	{
		"build" : "/Users/azabell/Desktop/ClangStructPointerExample/example10_glib_lib_workSpace/AttributeStruct/cmake-build-debug",
		"source" : "/Users/azabell/Desktop/ClangStructPointerExample/example10_glib_lib_workSpace/AttributeStruct"
	},
	"version" : 
	{
		"major" : 2,
		"minor" : 3
	}
}
